kestrapy/__init__.py
kestrapy/api_client.py
kestrapy/api_response.py
kestrapy/configuration.py
kestrapy/exceptions.py
kestrapy/kestra_client.py
kestrapy/py.typed
kestrapy/rest.py
kestrapy/api/__init__.py
kestrapy/api/executions_api.py
kestrapy/api/flows_api.py
kestrapy/api/groups_api.py
kestrapy/api/kv_api.py
kestrapy/api/namespaces_api.py
kestrapy/api/roles_api.py
kestrapy/api/service_account_api.py
kestrapy/api/triggers_api.py
kestrapy/api/users_api.py
kestrapy/models/__init__.py
kestrapy/models/abstract_flow.py
kestrapy/models/abstract_graph.py
kestrapy/models/abstract_graph_branch_type.py
kestrapy/models/abstract_metric_entry_object.py
kestrapy/models/abstract_trigger.py
kestrapy/models/abstract_trigger_for_execution.py
kestrapy/models/abstract_user.py
kestrapy/models/abstract_user_tenant_identity_provider.py
kestrapy/models/action.py
kestrapy/models/api_auth.py
kestrapy/models/api_autocomplete.py
kestrapy/models/api_group_summary.py
kestrapy/models/api_ids.py
kestrapy/models/api_patch_super_admin_request.py
kestrapy/models/api_role_summary.py
kestrapy/models/api_secret_list_response_api_secret_meta.py
kestrapy/models/api_secret_meta.py
kestrapy/models/api_secret_meta_ee.py
kestrapy/models/api_secret_tag.py
kestrapy/models/api_secret_value.py
kestrapy/models/api_tenant.py
kestrapy/models/api_tenant_summary.py
kestrapy/models/api_token.py
kestrapy/models/api_token_list.py
kestrapy/models/api_user.py
kestrapy/models/app_response.py
kestrapy/models/app_response_ui_layout.py
kestrapy/models/apps_controller_api_app.py
kestrapy/models/apps_controller_api_app_catalog_item.py
kestrapy/models/apps_controller_api_app_source.py
kestrapy/models/apps_controller_api_app_tags.py
kestrapy/models/apps_controller_api_bulk_import_response.py
kestrapy/models/apps_controller_api_bulk_import_response_error.py
kestrapy/models/apps_controller_api_bulk_operation_request.py
kestrapy/models/assertion.py
kestrapy/models/assertion_result.py
kestrapy/models/assertion_run_error.py
kestrapy-1.0.8.dist-info/METADATA
kestrapy-1.0.8.dist-info/WHEEL
kestrapy-1.0.8.dist-info/top_level.txt
kestrapy-1.0.8.dist-info/RECORD
