Metadata-Version: 2.4
Name: kestrapy
Version: 1.0.8
Summary: Kestra EE
Home-page: 
Author: OpenAPI Generator community
Author-email: OpenAPI Generator Community <team@openapitools.org>
Project-URL: Repository, https://github.com/GIT_USER_ID/GIT_REPO_ID
Keywords: OpenAPI,OpenAPI-Generator,Kestra EE
Requires-Python: >=3.9
Requires-Dist: requests>=2.32.5
Requires-Dist: sseclient-py>=1.8.0
Requires-Dist: urllib3<3.0.0,>=2.1.0
Requires-Dist: python-dateutil>=2.8.2
Requires-Dist: pydantic>=2
Requires-Dist: typing-extensions>=4.7.1
Dynamic: author
